{
    "containerDefinitions": [
        {
            "name": "CONTAINER_NAME",
            "image": "REPOSITORY_URI:BUILD_NUMBER",
            "cpu": 0,
            "portMappings": [
                {
                    
                    "containerPort": 8080,
                    "hostPort": 8080,
                    "protocol": "tcp",
                    "appProtocol": "http"
                }
            ],
            "essential": true,
            "environment": [],
            "environmentFiles": [],
            "mountPoints": [],
            "volumesFrom": [],
            "ulimits": [],
            "systemControls": []
        }
    ],
    "family": "FAMILY_NAME",
    "executionRoleArn": "arn:aws:iam::291579589752:role/ecsTaskExecutionRole",
    "networkMode": "bridge",
    "placementConstraints": [],
    "requiresCompatibilities": [
        "EC2"
    ],
    "cpu": "256",
    "memory": "512",
    "runtimePlatform": {
        "cpuArchitecture": "X86_64",
        "operatingSystemFamily": "LINUX"
    }
}